ajuste_ebo/__init__.py
ajuste_ebo/modulo.py
ajuste_ebo-0.1.1.dist-info/METADATA
ajuste_ebo-0.1.1.dist-info/WHEEL
ajuste_ebo-0.1.1.dist-info/top_level.txt
ajuste_ebo-0.1.1.dist-info/RECORD
