Metadata-Version: 2.1
Name: ajuste-ebo
Version: 0.1.1
Summary: Libreria para realizar ajustes de curva con 3 tipos de         kernels, gaussiano, tricube , Epanechnikov
Author: Emmanuel Botero  
Author-email: emmanuel.botero@udea.edu.co
License: MIT
Requires-Python: >=3.10.12
Requires-Dist: tqdm ==4.66.1
Requires-Dist: numpy ==1.26.1
Requires-Dist: pandas ==2.1.2
Requires-Dist: matplotlib ==3.8.1
